{"date":"1974-07-20","data":[{"song":"Rock Your Baby","artist":"George McCrae","this_week":1,"last_week":1,"peak_position":1,"weeks_on_chart":8},{"song":"Annie's Song","artist":"John Denver","this_week":2,"last_week":2,"peak_position":2,"weeks_on_chart":8},{"song":"Rock And Roll Heaven","artist":"The Righteous Brothers","this_week":3,"last_week":10,"peak_position":3,"weeks_on_chart":9},{"song":"Don't Let The Sun Go Down On Me","artist":"Elton John","this_week":4,"last_week":6,"peak_position":4,"weeks_on_chart":5},{"song":"On And On","artist":"Gladys Knight And The Pips","this_week":5,"last_week":5,"peak_position":5,"weeks_on_chart":9},{"song":"Rock The Boat","artist":"The Hues Corporation","this_week":6,"last_week":3,"peak_position":1,"weeks_on_chart":9},{"song":"Rikki Don't Lose That Number","artist":"Steely Dan","this_week":7,"last_week":13,"peak_position":7,"weeks_on_chart":11},{"song":"You Won't See Me","artist":"Anne Murray","this_week":8,"last_week":8,"peak_position":8,"weeks_on_chart":14},{"song":"The Air That I Breathe","artist":"The Hollies","this_week":9,"last_week":9,"peak_position":9,"weeks_on_chart":14},{"song":"If You Love Me (let Me Know)","artist":"Olivia Newton-John","this_week":10,"last_week":12,"peak_position":5,"weeks_on_chart":15},{"song":"Sideshow","artist":"Blue Magic","this_week":11,"last_week":14,"peak_position":11,"weeks_on_chart":10},{"song":"Sundown","artist":"Gordon Lightfoot","this_week":12,"last_week":4,"peak_position":1,"weeks_on_chart":15},{"song":"Billy, Don't Be A Hero","artist":"Bo Donaldson And The Heywoods","this_week":13,"last_week":7,"peak_position":1,"weeks_on_chart":14},{"song":"One Hell Of A Woman","artist":"Mac Davis","this_week":14,"last_week":11,"peak_position":11,"weeks_on_chart":17},{"song":"Radar Love","artist":"Golden Earring","this_week":15,"last_week":16,"peak_position":15,"weeks_on_chart":11},{"song":"Feel Like Makin' Love","artist":"Roberta Flack","this_week":16,"last_week":22,"peak_position":16,"weeks_on_chart":5},{"song":"Finally Got Myself Together (I'm A Changed Man)","artist":"The Impressions","this_week":17,"last_week":21,"peak_position":17,"weeks_on_chart":12},{"song":"Waterloo","artist":"ABBA","this_week":18,"last_week":18,"peak_position":18,"weeks_on_chart":8},{"song":"Please Come To Boston","artist":"Dave Loggins","this_week":19,"last_week":23,"peak_position":19,"weeks_on_chart":8},{"song":"Takin' Care Of Business","artist":"Bachman-Turner Overdrive","this_week":20,"last_week":24,"peak_position":20,"weeks_on_chart":10},{"song":"If You Talk In Your Sleep","artist":"Elvis Presley","this_week":21,"last_week":25,"peak_position":21,"weeks_on_chart":7},{"song":"Machine Gun","artist":"Commodores","this_week":22,"last_week":26,"peak_position":22,"weeks_on_chart":6},{"song":"Call On Me","artist":"Chicago","this_week":23,"last_week":27,"peak_position":23,"weeks_on_chart":5},{"song":"This Heart","artist":"Gene Redding","this_week":24,"last_week":28,"peak_position":24,"weeks_on_chart":12},{"song":"Tell Me Something Good","artist":"Rufus Featuring Chaka Khan","this_week":25,"last_week":39,"peak_position":25,"weeks_on_chart":6},{"song":"Band On The Run","artist":"Paul McCartney And Wings","this_week":26,"last_week":15,"peak_position":1,"weeks_on_chart":14},{"song":"Be Thankful For What You Got","artist":"William DeVaughn","this_week":27,"last_week":20,"peak_position":4,"weeks_on_chart":12},{"song":"Keep On Smilin'","artist":"Wet Willie","this_week":28,"last_week":35,"peak_position":28,"weeks_on_chart":9},{"song":"Fish Ain't Bitin'","artist":"Lamont Dozier","this_week":29,"last_week":34,"peak_position":29,"weeks_on_chart":6},{"song":"Come Monday","artist":"Jimmy Buffett","this_week":30,"last_week":30,"peak_position":30,"weeks_on_chart":10},{"song":"Sure As I'm Sittin' Here","artist":"Three Dog Night","this_week":31,"last_week":38,"peak_position":31,"weeks_on_chart":4},{"song":"The Night Chicago Died","artist":"Paper Lace","this_week":32,"last_week":40,"peak_position":32,"weeks_on_chart":6},{"song":"Ballero","artist":"War","this_week":33,"last_week":36,"peak_position":33,"weeks_on_chart":7},{"song":"Shinin' On","artist":"Grand Funk","this_week":34,"last_week":63,"peak_position":34,"weeks_on_chart":2},{"song":"Wildwood Weed","artist":"Jim Stafford","this_week":35,"last_week":62,"peak_position":35,"weeks_on_chart":3},{"song":"Rock Me Gently","artist":"Andy Kim","this_week":36,"last_week":42,"peak_position":36,"weeks_on_chart":5},{"song":"You And Me Against The World","artist":"Helen Reddy","this_week":37,"last_week":43,"peak_position":37,"weeks_on_chart":6},{"song":"Hollywood Swinging","artist":"Kool & The Gang","this_week":38,"last_week":17,"peak_position":6,"weeks_on_chart":14},{"song":"Hang On In There Baby","artist":"Johnny Bristol","this_week":39,"last_week":52,"peak_position":39,"weeks_on_chart":4},{"song":"Workin' At The Car Wash Blues","artist":"Jim Croce","this_week":40,"last_week":32,"peak_position":32,"weeks_on_chart":7},{"song":"The Streak","artist":"Ray Stevens","this_week":41,"last_week":29,"peak_position":1,"weeks_on_chart":15},{"song":"(You're) Having My Baby","artist":"Paul Anka with Odia Coates","this_week":42,"last_week":58,"peak_position":42,"weeks_on_chart":3},{"song":"My Thang","artist":"James Brown","this_week":43,"last_week":51,"peak_position":43,"weeks_on_chart":5},{"song":"Wild Thing","artist":"Fancy","this_week":44,"last_week":55,"peak_position":44,"weeks_on_chart":6},{"song":"Kung Fu","artist":"Curtis Mayfield","this_week":45,"last_week":69,"peak_position":45,"weeks_on_chart":5},{"song":"Midnight At The Oasis","artist":"Maria Muldaur","this_week":46,"last_week":31,"peak_position":6,"weeks_on_chart":22},{"song":"Dancing Machine","artist":"Jackson 5","this_week":47,"last_week":33,"peak_position":2,"weeks_on_chart":19},{"song":"Put Out The Light","artist":"Joe Cocker","this_week":48,"last_week":53,"peak_position":48,"weeks_on_chart":5},{"song":"Rub It In","artist":"Billy \"Crash\" Craddock","this_week":49,"last_week":64,"peak_position":49,"weeks_on_chart":4},{"song":"I'm Leaving It (All) Up To You","artist":"Donny & Marie Osmond","this_week":50,"last_week":65,"peak_position":50,"weeks_on_chart":3},{"song":"I'm Coming Home","artist":"The Spinners","this_week":51,"last_week":37,"peak_position":18,"weeks_on_chart":10},{"song":"You Make Me Feel Brand New","artist":"The Stylistics","this_week":52,"last_week":19,"peak_position":2,"weeks_on_chart":18},{"song":"Haven't Got Time For The Pain","artist":"Carly Simon","this_week":53,"last_week":44,"peak_position":14,"weeks_on_chart":11},{"song":"Jive Turkey (Part 1)","artist":"Ohio Players","this_week":54,"last_week":47,"peak_position":47,"weeks_on_chart":6},{"song":"Room Full Of Roses","artist":"Mickey Gilley","this_week":55,"last_week":50,"peak_position":50,"weeks_on_chart":7},{"song":"Save The Last Dance For Me","artist":"The DeFranco Family featuring Tony DeFranco","this_week":56,"last_week":49,"peak_position":18,"weeks_on_chart":12},{"song":"Already Gone","artist":"Eagles","this_week":57,"last_week":48,"peak_position":32,"weeks_on_chart":12},{"song":"Train Of Thought","artist":"Cher","this_week":58,"last_week":41,"peak_position":27,"weeks_on_chart":9},{"song":"If You Wanna Get To Heaven","artist":"Ozark Mountain Daredevils","this_week":59,"last_week":45,"peak_position":25,"weeks_on_chart":14},{"song":"Nothing From Nothing","artist":"Billy Preston","this_week":60,"last_week":70,"peak_position":60,"weeks_on_chart":2},{"song":"La Grange","artist":"ZZ Top","this_week":61,"last_week":54,"peak_position":41,"weeks_on_chart":17},{"song":"I Shot The Sheriff","artist":"Eric Clapton","this_week":62,"last_week":76,"peak_position":62,"weeks_on_chart":2},{"song":"There Will Never Be Any Peace (Until God Is Seated At The Conference Table)","artist":"The Chi-lites","this_week":63,"last_week":66,"peak_position":63,"weeks_on_chart":6},{"song":"My Girl Bill","artist":"Jim Stafford","this_week":64,"last_week":57,"peak_position":12,"weeks_on_chart":14},{"song":"Happiness Is Just Around The Bend","artist":"The Main Ingredient","this_week":65,"last_week":71,"peak_position":65,"weeks_on_chart":4},{"song":"For The Love Of Money","artist":"The O'Jays","this_week":66,"last_week":46,"peak_position":9,"weeks_on_chart":15},{"song":"It's Better To Have (and Don't Need)","artist":"Don Covay","this_week":67,"last_week":72,"peak_position":67,"weeks_on_chart":2},{"song":"The Loco-Motion","artist":"Grand Funk","this_week":68,"last_week":60,"peak_position":1,"weeks_on_chart":20},{"song":"Old Home Filler-up An' Keep On-a-truckin' Cafe","artist":"C.W. McCall","this_week":69,"last_week":75,"peak_position":69,"weeks_on_chart":4},{"song":"You're Welcome, Stop On By","artist":"Bobby Womack","this_week":70,"last_week":96,"peak_position":70,"weeks_on_chart":3},{"song":"Clap For The Wolfman","artist":"The Guess Who","this_week":71,"last_week":null,"peak_position":71,"weeks_on_chart":1},{"song":"River's Risin'","artist":"Edgar Winter","this_week":72,"last_week":null,"peak_position":72,"weeks_on_chart":1},{"song":"Dance Master Pt. 1","artist":"Willie Henderson","this_week":73,"last_week":88,"peak_position":73,"weeks_on_chart":3},{"song":"Beach Baby","artist":"First Class","this_week":74,"last_week":null,"peak_position":74,"weeks_on_chart":1},{"song":"Between Her Goodbye And My Hello","artist":"Gladys Knight And The Pips","this_week":75,"last_week":86,"peak_position":75,"weeks_on_chart":4},{"song":"Don't Knock My Love","artist":"Diana Ross & Marvin Gaye","this_week":76,"last_week":90,"peak_position":76,"weeks_on_chart":2},{"song":"Time For Livin'","artist":"Sly & The Family Stone","this_week":77,"last_week":87,"peak_position":77,"weeks_on_chart":3},{"song":"Kalimba Story","artist":"Earth, Wind & Fire","this_week":78,"last_week":82,"peak_position":78,"weeks_on_chart":2},{"song":"Rings","artist":"Lobo","this_week":79,"last_week":null,"peak_position":79,"weeks_on_chart":1},{"song":"Secretary","artist":"Betty Wright","this_week":80,"last_week":84,"peak_position":80,"weeks_on_chart":2},{"song":"Sugar Baby Love","artist":"The Rubettes","this_week":81,"last_week":null,"peak_position":81,"weeks_on_chart":1},{"song":"Don't Change Horses (In The Middle Of A Stream)","artist":"Tower Of Power","this_week":82,"last_week":null,"peak_position":82,"weeks_on_chart":1},{"song":"How Do You Feel The Morning After","artist":"Millie Jackson","this_week":83,"last_week":77,"peak_position":77,"weeks_on_chart":7},{"song":"Help Me","artist":"Joni Mitchell","this_week":84,"last_week":67,"peak_position":7,"weeks_on_chart":19},{"song":"The Show Must Go On","artist":"Three Dog Night","this_week":85,"last_week":73,"peak_position":4,"weeks_on_chart":19},{"song":"Rings","artist":"Reuben Howell","this_week":86,"last_week":null,"peak_position":86,"weeks_on_chart":1},{"song":"I've Been Born Again","artist":"Johnnie Taylor","this_week":87,"last_week":78,"peak_position":78,"weeks_on_chart":4},{"song":"You've Got My Soul On Fire","artist":"The Temptations","this_week":88,"last_week":74,"peak_position":74,"weeks_on_chart":5},{"song":"Rebel Rebel","artist":"David Bowie","this_week":89,"last_week":68,"peak_position":64,"weeks_on_chart":8},{"song":"I've Had It","artist":"Fanny","this_week":90,"last_week":95,"peak_position":79,"weeks_on_chart":7},{"song":"Walk On","artist":"Neil Young","this_week":91,"last_week":91,"peak_position":91,"weeks_on_chart":2},{"song":"Air Disaster","artist":"Albert Hammond","this_week":92,"last_week":81,"peak_position":81,"weeks_on_chart":4},{"song":"Tell Me That I'm Wrong","artist":"Blood, Sweat & Tears","this_week":93,"last_week":83,"peak_position":83,"weeks_on_chart":4},{"song":"You Can't Be A Beacon (if Your Light Don't Shine)","artist":"Donna Fargo","this_week":94,"last_week":79,"peak_position":79,"weeks_on_chart":4},{"song":"Worse Comes To Worst","artist":"Billy Joel","this_week":95,"last_week":80,"peak_position":80,"weeks_on_chart":4},{"song":"Love Is The Message","artist":"MFSB Featuring The Three Degrees","this_week":96,"last_week":85,"peak_position":85,"weeks_on_chart":3},{"song":"Good Things Don't Last Forever","artist":"Ecstasy, Passion & Pain","this_week":97,"last_week":93,"peak_position":93,"weeks_on_chart":3},{"song":"American Girls","artist":"Rick Springfield","this_week":98,"last_week":98,"peak_position":98,"weeks_on_chart":2},{"song":"It Could Have Been Me","artist":"Sami Jo","this_week":99,"last_week":99,"peak_position":99,"weeks_on_chart":2},{"song":"Ma! (He's Making Eyes At Me)","artist":"Lena Zavaroni","this_week":100,"last_week":100,"peak_position":100,"weeks_on_chart":2}]}