{"date":"1990-06-23","data":[{"song":"It Must Have Been Love (From \"Pretty Woman\")","artist":"Roxette","this_week":1,"last_week":1,"peak_position":1,"weeks_on_chart":12},{"song":"Step By Step","artist":"New Kids On The Block","this_week":2,"last_week":4,"peak_position":2,"weeks_on_chart":5},{"song":"Poison","artist":"Bell Biv DeVoe","this_week":3,"last_week":3,"peak_position":3,"weeks_on_chart":12},{"song":"Hold On","artist":"Wilson Phillips","this_week":4,"last_week":2,"peak_position":1,"weeks_on_chart":15},{"song":"Do You Remember?","artist":"Phil Collins","this_week":5,"last_week":10,"peak_position":5,"weeks_on_chart":9},{"song":"Vogue","artist":"Madonna","this_week":6,"last_week":5,"peak_position":1,"weeks_on_chart":11},{"song":"Ready Or Not","artist":"After 7","this_week":7,"last_week":9,"peak_position":7,"weeks_on_chart":13},{"song":"Hold On","artist":"En Vogue","this_week":8,"last_week":11,"peak_position":8,"weeks_on_chart":8},{"song":"U Can't Touch This","artist":"M.C. Hammer","this_week":9,"last_week":8,"peak_position":8,"weeks_on_chart":9},{"song":"I'll Be Your Shelter","artist":"Taylor Dayne","this_week":10,"last_week":14,"peak_position":10,"weeks_on_chart":8},{"song":"All I Wanna Do Is Make Love To You","artist":"Heart","this_week":11,"last_week":6,"peak_position":2,"weeks_on_chart":13},{"song":"She Ain't Worth It","artist":"Glenn Medeiros Featuring Bobby Brown","this_week":12,"last_week":18,"peak_position":12,"weeks_on_chart":6},{"song":"Children Of The Night","artist":"Richard Marx","this_week":13,"last_week":15,"peak_position":13,"weeks_on_chart":9},{"song":"The Humpty Dance","artist":"Digital Underground","this_week":14,"last_week":12,"peak_position":11,"weeks_on_chart":15},{"song":"Rub You The Right Way","artist":"Johnny Gill","this_week":15,"last_week":19,"peak_position":15,"weeks_on_chart":7},{"song":"Baby, It's Tonight","artist":"Jude Cole","this_week":16,"last_week":16,"peak_position":16,"weeks_on_chart":11},{"song":"Cradle Of Love (From \"Ford Fairlane\")","artist":"Billy Idol","this_week":17,"last_week":21,"peak_position":17,"weeks_on_chart":8},{"song":"Sending All My Love","artist":"Linear","this_week":18,"last_week":13,"peak_position":5,"weeks_on_chart":19},{"song":"Enjoy The Silence","artist":"Depeche Mode","this_week":19,"last_week":22,"peak_position":19,"weeks_on_chart":11},{"song":"Alright","artist":"Janet Jackson","this_week":20,"last_week":7,"peak_position":4,"weeks_on_chart":12},{"song":"The Power","artist":"Snap!","this_week":21,"last_week":25,"peak_position":21,"weeks_on_chart":7},{"song":"Girls Nite Out","artist":"Tyler Collins","this_week":22,"last_week":27,"peak_position":22,"weeks_on_chart":9},{"song":"Sittin' In The Lap Of Luxury","artist":"Louie Louie","this_week":23,"last_week":26,"peak_position":23,"weeks_on_chart":9},{"song":"Nothing Compares 2 U","artist":"Sinead O'Connor","this_week":24,"last_week":17,"peak_position":1,"weeks_on_chart":15},{"song":"Notice Me","artist":"Nikki","this_week":25,"last_week":30,"peak_position":25,"weeks_on_chart":9},{"song":"Turtle Power","artist":"Partners In Kryme","this_week":26,"last_week":20,"peak_position":13,"weeks_on_chart":10},{"song":"Up All Night","artist":"Slaughter","this_week":27,"last_week":28,"peak_position":27,"weeks_on_chart":9},{"song":"When I'm Back On My Feet Again","artist":"Michael Bolton","this_week":28,"last_week":31,"peak_position":28,"weeks_on_chart":5},{"song":"Mentirosa","artist":"Mellow Man Ace","this_week":29,"last_week":33,"peak_position":29,"weeks_on_chart":7},{"song":"Ooh La La (I Can't Get Over You)","artist":"Perfect Gentlemen","this_week":30,"last_week":23,"peak_position":10,"weeks_on_chart":11},{"song":"Vision Of Love","artist":"Mariah Carey","this_week":31,"last_week":38,"peak_position":31,"weeks_on_chart":4},{"song":"You Can't Deny It","artist":"Lisa Stansfield","this_week":32,"last_week":37,"peak_position":32,"weeks_on_chart":5},{"song":"Dare To Fall In Love","artist":"Brent Bourgeois","this_week":33,"last_week":32,"peak_position":32,"weeks_on_chart":9},{"song":"The Ballad Of Jayne","artist":"L.A. Guns","this_week":34,"last_week":34,"peak_position":34,"weeks_on_chart":12},{"song":"Club At The End Of The Street","artist":"Elton John","this_week":35,"last_week":35,"peak_position":35,"weeks_on_chart":9},{"song":"I'll See You In My Dreams","artist":"Giant","this_week":36,"last_week":24,"peak_position":20,"weeks_on_chart":14},{"song":"Nicety","artist":"Michel'le","this_week":37,"last_week":29,"peak_position":29,"weeks_on_chart":11},{"song":"King Of Wishful Thinking (From \"Pretty Woman\")","artist":"Go West","this_week":38,"last_week":44,"peak_position":38,"weeks_on_chart":6},{"song":"Love Is","artist":"Alannah Myles","this_week":39,"last_week":40,"peak_position":39,"weeks_on_chart":8},{"song":"Bad Of The Heart","artist":"George LaMond","this_week":40,"last_week":45,"peak_position":40,"weeks_on_chart":7},{"song":"Make You Sweat","artist":"Keith Sweat","this_week":41,"last_week":52,"peak_position":41,"weeks_on_chart":4},{"song":"When I Dream Of You","artist":"Tommy Page","this_week":42,"last_week":43,"peak_position":42,"weeks_on_chart":7},{"song":"Kiss This Thing Goodbye","artist":"Del Amitri","this_week":43,"last_week":47,"peak_position":43,"weeks_on_chart":6},{"song":"Don't Go Away Mad (Just Go Away)","artist":"Motley Crue","this_week":44,"last_week":48,"peak_position":44,"weeks_on_chart":4},{"song":"I Wanna Be Rich","artist":"Calloway","this_week":45,"last_week":36,"peak_position":2,"weeks_on_chart":20},{"song":"Expression","artist":"Salt-N-Pepa","this_week":46,"last_week":46,"peak_position":26,"weeks_on_chart":16},{"song":"Always And Forever","artist":"Whistle","this_week":47,"last_week":39,"peak_position":35,"weeks_on_chart":12},{"song":"If Wishes Came True","artist":"Sweet Sensation","this_week":48,"last_week":58,"peak_position":48,"weeks_on_chart":2},{"song":"Could This Be Love","artist":"Seduction","this_week":49,"last_week":55,"peak_position":49,"weeks_on_chart":3},{"song":"Doubleback (From \"Back To The Future Part III\")","artist":"ZZ Top","this_week":50,"last_week":51,"peak_position":50,"weeks_on_chart":6},{"song":"The Blues","artist":"Tony Toni Tone","this_week":51,"last_week":56,"peak_position":51,"weeks_on_chart":4},{"song":"House Of Pain","artist":"Faster Pussycat","this_week":52,"last_week":50,"peak_position":28,"weeks_on_chart":18},{"song":"Pure","artist":"Lightning Seeds","this_week":53,"last_week":57,"peak_position":53,"weeks_on_chart":6},{"song":"Possession","artist":"Bad English","this_week":54,"last_week":64,"peak_position":54,"weeks_on_chart":3},{"song":"Your Baby Never Looked Good In Blue","artist":"Expose","this_week":55,"last_week":41,"peak_position":17,"weeks_on_chart":13},{"song":"Welcome To The Real World","artist":"Jane Child","this_week":56,"last_week":60,"peak_position":56,"weeks_on_chart":4},{"song":"\"B\" Girls","artist":"Young And Restless","this_week":57,"last_week":54,"peak_position":54,"weeks_on_chart":8},{"song":"This Old Heart Of Mine","artist":"Rod Stewart With Ronald Isley","this_week":58,"last_week":42,"peak_position":10,"weeks_on_chart":14},{"song":"Bounce Back","artist":"Alisha","this_week":59,"last_week":63,"peak_position":59,"weeks_on_chart":5},{"song":"My Kinda Girl","artist":"Babyface","this_week":60,"last_week":71,"peak_position":60,"weeks_on_chart":2},{"song":"What It Takes","artist":"Aerosmith","this_week":61,"last_week":53,"peak_position":9,"weeks_on_chart":15},{"song":"Show Me","artist":"Howard Hewett","this_week":62,"last_week":65,"peak_position":62,"weeks_on_chart":5},{"song":"Across The River","artist":"Bruce Hornsby & The Range","this_week":63,"last_week":null,"peak_position":63,"weeks_on_chart":1},{"song":"Deadbeat Club","artist":"The B-52s","this_week":64,"last_week":49,"peak_position":30,"weeks_on_chart":10},{"song":"The Right Combination","artist":"Seiko & Donnie Wahlberg","this_week":65,"last_week":88,"peak_position":65,"weeks_on_chart":2},{"song":"Bang Bang","artist":"Danger Danger","this_week":66,"last_week":81,"peak_position":66,"weeks_on_chart":4},{"song":"I Didn't Want To Need You","artist":"Heart","this_week":67,"last_week":null,"peak_position":67,"weeks_on_chart":1},{"song":"Let Me Be Your Lover","artist":"The U-Krew","this_week":68,"last_week":79,"peak_position":68,"weeks_on_chart":3},{"song":"The Girl I Used To Know","artist":"Brother Beyond","this_week":69,"last_week":null,"peak_position":69,"weeks_on_chart":1},{"song":"Counting The Days","artist":"Joey Kid","this_week":70,"last_week":70,"peak_position":70,"weeks_on_chart":8},{"song":"Epic","artist":"Faith No More","this_week":71,"last_week":null,"peak_position":71,"weeks_on_chart":1},{"song":"How Can We Be Lovers","artist":"Michael Bolton","this_week":72,"last_week":61,"peak_position":3,"weeks_on_chart":17},{"song":"The Heart Of The Matter","artist":"Don Henley","this_week":73,"last_week":67,"peak_position":21,"weeks_on_chart":19},{"song":"The Other Side","artist":"Aerosmith","this_week":74,"last_week":null,"peak_position":74,"weeks_on_chart":1},{"song":"Jealous Again","artist":"The Black Crowes","this_week":75,"last_week":78,"peak_position":75,"weeks_on_chart":7},{"song":"Don't Wanna Fall In Love","artist":"Jane Child","this_week":76,"last_week":59,"peak_position":2,"weeks_on_chart":20},{"song":"Follow My Heartbeat","artist":"A'me Lorain","this_week":77,"last_week":92,"peak_position":77,"weeks_on_chart":2},{"song":"All Around The World","artist":"Lisa Stansfield","this_week":78,"last_week":68,"peak_position":3,"weeks_on_chart":21},{"song":"Coming Of Age","artist":"Damn Yankees","this_week":79,"last_week":76,"peak_position":60,"weeks_on_chart":10},{"song":"We're All In the Same Gang","artist":"The West Coast Rap All-Stars","this_week":80,"last_week":null,"peak_position":80,"weeks_on_chart":1},{"song":"Got To Tell Me Something","artist":"Ana","this_week":81,"last_week":66,"peak_position":66,"weeks_on_chart":6},{"song":"Rise To It","artist":"KISS","this_week":82,"last_week":84,"peak_position":82,"weeks_on_chart":3},{"song":"Time After Time","artist":"Timmy T.","this_week":83,"last_week":82,"peak_position":40,"weeks_on_chart":16},{"song":"Don't You Love Me","artist":"49-ers","this_week":84,"last_week":91,"peak_position":84,"weeks_on_chart":2},{"song":"Love Child","artist":"Sweet Sensation","this_week":85,"last_week":73,"peak_position":13,"weeks_on_chart":15},{"song":"Talk To Me","artist":"Anita Baker","this_week":86,"last_week":null,"peak_position":86,"weeks_on_chart":1},{"song":"The Downeaster \"Alexa\"","artist":"Billy Joel","this_week":87,"last_week":77,"peak_position":57,"weeks_on_chart":8},{"song":"Chain Of Fools","artist":"Little Caesar","this_week":88,"last_week":93,"peak_position":88,"weeks_on_chart":2},{"song":"Here And Now","artist":"Luther Vandross","this_week":89,"last_week":72,"peak_position":6,"weeks_on_chart":27},{"song":"Cruising For Bruising","artist":"Basia","this_week":90,"last_week":62,"peak_position":29,"weeks_on_chart":12},{"song":"I Melt With You","artist":"Modern English","this_week":91,"last_week":null,"peak_position":78,"weeks_on_chart":8},{"song":"Whip Appeal","artist":"Babyface","this_week":92,"last_week":74,"peak_position":6,"weeks_on_chart":18},{"song":"Get A Life","artist":"Soul II Soul","this_week":93,"last_week":86,"peak_position":54,"weeks_on_chart":11},{"song":"The Emperor's New Clothes","artist":"Sinead O'Connor","this_week":94,"last_week":null,"peak_position":94,"weeks_on_chart":1},{"song":"Tomorrow (A Better You, Better Me)","artist":"Quincy Jones With Tevin Campbell","this_week":95,"last_week":75,"peak_position":75,"weeks_on_chart":5},{"song":"What Are You Doing With A Fool Like Me","artist":"Joe Cocker","this_week":96,"last_week":null,"peak_position":96,"weeks_on_chart":1},{"song":"If U Were Mine","artist":"The U-Krew","this_week":97,"last_week":69,"peak_position":24,"weeks_on_chart":22},{"song":"Room At The Top","artist":"Adam Ant","this_week":98,"last_week":80,"peak_position":17,"weeks_on_chart":16},{"song":"All That Glitters Isn't Gold","artist":"The Cover Girls","this_week":99,"last_week":85,"peak_position":49,"weeks_on_chart":12},{"song":"That's The Way Of The World","artist":"D-Mob With Cathy Dennis","this_week":100,"last_week":87,"peak_position":59,"weeks_on_chart":9}]}