{"date":"2009-01-31","data":[{"song":"Just Dance","artist":"Lady Gaga Featuring Colby O'Donis","this_week":1,"last_week":1,"peak_position":1,"weeks_on_chart":24},{"song":"Single Ladies (Put A Ring On It)","artist":"Beyonce","this_week":2,"last_week":2,"peak_position":1,"weeks_on_chart":14},{"song":"Heartless","artist":"Kanye West","this_week":3,"last_week":3,"peak_position":3,"weeks_on_chart":11},{"song":"Live Your Life","artist":"T.I. Featuring Rihanna","this_week":4,"last_week":4,"peak_position":1,"weeks_on_chart":17},{"song":"Love Story","artist":"Taylor Swift","this_week":5,"last_week":5,"peak_position":4,"weeks_on_chart":19},{"song":"Gives You Hell","artist":"The All-American Rejects","this_week":6,"last_week":10,"peak_position":6,"weeks_on_chart":10},{"song":"I'm Yours","artist":"Jason Mraz","this_week":7,"last_week":7,"peak_position":6,"weeks_on_chart":40},{"song":"Hot N Cold","artist":"Katy Perry","this_week":8,"last_week":6,"peak_position":3,"weeks_on_chart":25},{"song":"Let It Rock","artist":"Kevin Rudolf Featuring Lil Wayne","this_week":9,"last_week":8,"peak_position":5,"weeks_on_chart":21},{"song":"Circus","artist":"Britney Spears","this_week":10,"last_week":11,"peak_position":3,"weeks_on_chart":7},{"song":"I Hate This Part","artist":"The Pussycat Dolls","this_week":11,"last_week":18,"peak_position":11,"weeks_on_chart":8},{"song":"Womanizer","artist":"Britney Spears","this_week":12,"last_week":9,"peak_position":1,"weeks_on_chart":16},{"song":"Love Lockdown","artist":"Kanye West","this_week":13,"last_week":12,"peak_position":3,"weeks_on_chart":18},{"song":"Whatever You Like","artist":"T.I.","this_week":14,"last_week":13,"peak_position":1,"weeks_on_chart":24},{"song":"Right Now (Na Na Na)","artist":"Akon","this_week":15,"last_week":14,"peak_position":8,"weeks_on_chart":17},{"song":"You Found Me","artist":"The Fray","this_week":16,"last_week":20,"peak_position":15,"weeks_on_chart":9},{"song":"Gotta Be Somebody","artist":"Nickelback","this_week":17,"last_week":17,"peak_position":10,"weeks_on_chart":16},{"song":"Dead And Gone","artist":"T.I. Featuring Justin Timberlake","this_week":18,"last_week":30,"peak_position":18,"weeks_on_chart":7},{"song":"So What","artist":"P!nk","this_week":19,"last_week":16,"peak_position":1,"weeks_on_chart":22},{"song":"Sober","artist":"P!nk","this_week":20,"last_week":25,"peak_position":20,"weeks_on_chart":8},{"song":"Miss Independent","artist":"Ne-Yo","this_week":21,"last_week":15,"peak_position":7,"weeks_on_chart":22},{"song":"Untouched","artist":"The Veronicas","this_week":22,"last_week":21,"peak_position":21,"weeks_on_chart":8},{"song":"Light On","artist":"David Cook","this_week":23,"last_week":39,"peak_position":17,"weeks_on_chart":15},{"song":"Pop Champagne","artist":"Jim Jones & Ron Browz Featuring Juelz Santana","this_week":24,"last_week":22,"peak_position":22,"weeks_on_chart":14},{"song":"Mad","artist":"Ne-Yo","this_week":25,"last_week":33,"peak_position":25,"weeks_on_chart":7},{"song":"If I Were A Boy","artist":"Beyonce","this_week":26,"last_week":19,"peak_position":3,"weeks_on_chart":15},{"song":"Rehab","artist":"Rihanna","this_week":27,"last_week":23,"peak_position":18,"weeks_on_chart":11},{"song":"Green Light","artist":"John Legend Featuring Andre 3000","this_week":28,"last_week":26,"peak_position":24,"weeks_on_chart":20},{"song":"One More Drink","artist":"Ludacris Co-Starring T-Pain","this_week":29,"last_week":24,"peak_position":24,"weeks_on_chart":12},{"song":"Chicken Fried","artist":"Zac Brown Band","this_week":30,"last_week":27,"peak_position":20,"weeks_on_chart":18},{"song":"Viva La Vida","artist":"Coldplay","this_week":31,"last_week":29,"peak_position":1,"weeks_on_chart":37},{"song":"Disturbia","artist":"Rihanna","this_week":32,"last_week":28,"peak_position":1,"weeks_on_chart":31},{"song":"Addicted","artist":"Saving Abel","this_week":33,"last_week":31,"peak_position":20,"weeks_on_chart":32},{"song":"Chopped 'N' Skrewed","artist":"T-Pain Featuring Ludacris","this_week":34,"last_week":32,"peak_position":27,"weeks_on_chart":14},{"song":"White Horse","artist":"Taylor Swift","this_week":35,"last_week":37,"peak_position":13,"weeks_on_chart":10},{"song":"Better In Time","artist":"Leona Lewis","this_week":36,"last_week":38,"peak_position":11,"weeks_on_chart":28},{"song":"Diva","artist":"Beyonce","this_week":37,"last_week":51,"peak_position":37,"weeks_on_chart":5},{"song":"I'm So Paid","artist":"Akon Featuring Lil Wayne & Young Jeezy","this_week":38,"last_week":35,"peak_position":31,"weeks_on_chart":14},{"song":"Crush","artist":"David Archuleta","this_week":39,"last_week":47,"peak_position":2,"weeks_on_chart":23},{"song":"Mrs. Officer","artist":"Lil Wayne Featuring Bobby Valentino & Kidd Kidd","this_week":40,"last_week":34,"peak_position":16,"weeks_on_chart":22},{"song":"Beautiful","artist":"Akon Featuring Colby O'Donis & Kardinal Offishall","this_week":41,"last_week":43,"peak_position":19,"weeks_on_chart":7},{"song":"Feel That Fire","artist":"Dierks Bentley","this_week":42,"last_week":44,"peak_position":42,"weeks_on_chart":15},{"song":"Turnin Me On","artist":"Keri Hilson Featuring Lil Wayne","this_week":43,"last_week":61,"peak_position":43,"weeks_on_chart":5},{"song":"God Love Her","artist":"Toby Keith","this_week":44,"last_week":48,"peak_position":44,"weeks_on_chart":9},{"song":"She Wouldn't Be Gone","artist":"Blake Shelton","this_week":45,"last_week":49,"peak_position":45,"weeks_on_chart":13},{"song":"Shattered (Turn The Car Around)","artist":"O.A.R.","this_week":46,"last_week":41,"peak_position":36,"weeks_on_chart":24},{"song":"Human","artist":"The Killers","this_week":47,"last_week":42,"peak_position":32,"weeks_on_chart":16},{"song":"Poker Face","artist":"Lady Gaga","this_week":48,"last_week":72,"peak_position":48,"weeks_on_chart":5},{"song":"Country Boy","artist":"Alan Jackson","this_week":49,"last_week":55,"peak_position":49,"weeks_on_chart":12},{"song":"Kiss Me Thru The Phone","artist":"Soulja Boy Tell 'em Featuring Sammie","this_week":50,"last_week":60,"peak_position":50,"weeks_on_chart":4},{"song":"Cowgirls Don't Cry","artist":"Brooks & Dunn Featuring Reba McEntire","this_week":51,"last_week":52,"peak_position":51,"weeks_on_chart":10},{"song":"La La Land","artist":"Demi Lovato","this_week":52,"last_week":62,"peak_position":52,"weeks_on_chart":4},{"song":"Don't","artist":"Billy Currington","this_week":53,"last_week":59,"peak_position":53,"weeks_on_chart":13},{"song":"Put It On Ya","artist":"Plies Featuring Chris J","this_week":54,"last_week":46,"peak_position":31,"weeks_on_chart":9},{"song":"Decode","artist":"Paramore","this_week":55,"last_week":45,"peak_position":33,"weeks_on_chart":11},{"song":"I Don't Care","artist":"Fall Out Boy","this_week":56,"last_week":36,"peak_position":21,"weeks_on_chart":19},{"song":"Sweet Thing","artist":"Keith Urban","this_week":57,"last_week":71,"peak_position":43,"weeks_on_chart":10},{"song":"Start A Band","artist":"Brad Paisley Duet With Keith Urban","this_week":58,"last_week":58,"peak_position":55,"weeks_on_chart":14},{"song":"Down The Road","artist":"Kenny Chesney With Mac McAnally","this_week":59,"last_week":66,"peak_position":59,"weeks_on_chart":7},{"song":"Roll With Me","artist":"Montgomery Gentry","this_week":60,"last_week":54,"peak_position":33,"weeks_on_chart":19},{"song":"Rockin' That Thang","artist":"The-Dream","this_week":61,"last_week":76,"peak_position":61,"weeks_on_chart":4},{"song":"Second Chance","artist":"Shinedown","this_week":62,"last_week":69,"peak_position":60,"weeks_on_chart":8},{"song":"Already Gone","artist":"Sugarland","this_week":63,"last_week":53,"peak_position":41,"weeks_on_chart":17},{"song":"In Color","artist":"Jamey Johnson","this_week":64,"last_week":57,"peak_position":52,"weeks_on_chart":16},{"song":"She Got Her Own","artist":"Ne-Yo Featuring Jamie Foxx & Fabolous","this_week":65,"last_week":74,"peak_position":65,"weeks_on_chart":6},{"song":"Sex On Fire","artist":"Kings Of Leon","this_week":66,"last_week":64,"peak_position":56,"weeks_on_chart":13},{"song":"Trading Places","artist":"Usher","this_week":67,"last_week":56,"peak_position":45,"weeks_on_chart":12},{"song":"Just Like Me","artist":"Jamie Foxx Featuring T.I.","this_week":68,"last_week":67,"peak_position":49,"weeks_on_chart":6},{"song":"You're Gonna Go Far, Kid","artist":"The Offspring","this_week":69,"last_week":68,"peak_position":63,"weeks_on_chart":15},{"song":"Keeps Gettin' Better","artist":"Christina Aguilera","this_week":70,"last_week":63,"peak_position":7,"weeks_on_chart":16},{"song":"Don't Trust Me","artist":"3OH!3","this_week":71,"last_week":81,"peak_position":56,"weeks_on_chart":6},{"song":"Krazy","artist":"Pitbull Featuring Lil Jon","this_week":72,"last_week":73,"peak_position":30,"weeks_on_chart":17},{"song":"Here","artist":"Rascal Flatts","this_week":73,"last_week":65,"peak_position":50,"weeks_on_chart":16},{"song":"IfULeave","artist":"Musiq Soulchild Featuring Mary J. Blige","this_week":74,"last_week":80,"peak_position":71,"weeks_on_chart":8},{"song":"River Of Love","artist":"George Strait","this_week":75,"last_week":87,"peak_position":75,"weeks_on_chart":6},{"song":"It Won't Be Like This For Long","artist":"Darius Rucker","this_week":76,"last_week":88,"peak_position":76,"weeks_on_chart":3},{"song":"Tell Me Something I Don't Know","artist":"Selena Gomez","this_week":77,"last_week":null,"peak_position":77,"weeks_on_chart":2},{"song":"Crack A Bottle","artist":"Eminem, Dr. Dre & 50 Cent","this_week":78,"last_week":null,"peak_position":78,"weeks_on_chart":1},{"song":"Thinking Of You","artist":"Katy Perry","this_week":79,"last_week":null,"peak_position":79,"weeks_on_chart":1},{"song":"Swagga Like Us","artist":"Jay-Z & T.I. Featuring Kanye West & Lil Wayne","this_week":80,"last_week":70,"peak_position":5,"weeks_on_chart":19},{"song":"Playa Cardz Right","artist":"Keyshia Cole Featuring 2Pac","this_week":81,"last_week":82,"peak_position":63,"weeks_on_chart":10},{"song":"Lollipop","artist":"Framing Hanley","this_week":82,"last_week":95,"peak_position":82,"weeks_on_chart":3},{"song":"Broken","artist":"Lifehouse","this_week":83,"last_week":86,"peak_position":83,"weeks_on_chart":13},{"song":"Lucky","artist":"Jason Mraz & Colbie Caillat","this_week":84,"last_week":null,"peak_position":82,"weeks_on_chart":2},{"song":"I Don't Care","artist":"Apocalyptica Featuring Adam Gontier","this_week":85,"last_week":85,"peak_position":78,"weeks_on_chart":14},{"song":"Bust Your Windows","artist":"Jazmine Sullivan","this_week":86,"last_week":79,"peak_position":31,"weeks_on_chart":15},{"song":"Seventeen Forever","artist":"Metro Station","this_week":87,"last_week":77,"peak_position":42,"weeks_on_chart":6},{"song":"Day 'N' Nite","artist":"Kid Cudi","this_week":88,"last_week":null,"peak_position":88,"weeks_on_chart":1},{"song":"Lost","artist":"Gorilla Zoe","this_week":89,"last_week":93,"peak_position":89,"weeks_on_chart":2},{"song":"About You Now","artist":"Miranda Cosgrove","this_week":90,"last_week":84,"peak_position":47,"weeks_on_chart":4},{"song":"Bad Girlfriend","artist":"Theory Of A Deadman","this_week":91,"last_week":91,"peak_position":75,"weeks_on_chart":16},{"song":"Angels On The Moon","artist":"Thriving Ivory","this_week":92,"last_week":null,"peak_position":92,"weeks_on_chart":1},{"song":"Last Call","artist":"Lee Ann Womack","this_week":93,"last_week":null,"peak_position":93,"weeks_on_chart":1},{"song":"Lookin' For A Good Time","artist":"Lady Antebellum","this_week":94,"last_week":83,"peak_position":67,"weeks_on_chart":15},{"song":"Without You","artist":"Hinder","this_week":95,"last_week":89,"peak_position":85,"weeks_on_chart":9},{"song":"Beep","artist":"Bobby V Featuring Yung Joc","this_week":96,"last_week":94,"peak_position":94,"weeks_on_chart":3},{"song":"My Life Would Suck Without You","artist":"Kelly Clarkson","this_week":97,"last_week":null,"peak_position":97,"weeks_on_chart":1},{"song":"Blame It","artist":"Jamie Foxx Featuring T-Pain","this_week":98,"last_week":null,"peak_position":98,"weeks_on_chart":1},{"song":"More Like Her","artist":"Miranda Lambert","this_week":99,"last_week":null,"peak_position":99,"weeks_on_chart":1},{"song":"All Summer Long","artist":"The Rock Heroes","this_week":100,"last_week":90,"peak_position":29,"weeks_on_chart":15}]}